bear_epoch_time/__init__.py
bear_epoch_time/__main__.py
bear_epoch_time/constants.py
bear_epoch_time/epoch_timestamp.py
bear_epoch_time/helpers.py
bear_epoch_time/time_converter.py
bear_epoch_time/time_tools.py
bear_epoch_time/timer.py
bear_epoch_time/tz.py
bear_epoch_time/_internal/__init__.py
bear_epoch_time/_internal/_get_version.py
bear_epoch_time/_internal/_info.py
bear_epoch_time/_internal/_version.py
bear_epoch_time/_internal/cli.py
bear_epoch_time/_internal/debug.py
bear_epoch_time-1.2.10.dist-info/METADATA
bear_epoch_time-1.2.10.dist-info/WHEEL
bear_epoch_time-1.2.10.dist-info/entry_points.txt
bear_epoch_time-1.2.10.dist-info/RECORD
