Metadata-Version: 2.4
Name: bear-epoch-time
Version: 1.2.10
Summary: Elegant epoch timestamp handling with timezone-aware operations, fluent API, and smart defaults for Python developers who hate datetime complexity.
Author-email: chaz <bright.lid5647@fastmail.com>
Requires-Python: >=3.11
Requires-Dist: python-dateutil>=2.9.0.post0
Requires-Dist: pytz>=2025.2
Requires-Dist: tzlocal>=5.3.1
